superface/__init__.py
superface/agno/__init__.py
superface/agno/superface.py
superface/client/__init__.py
superface/client/exceptions.py
superface/client/schema_transformer.py
superface/client/superface.py
superface/crewai/__init__.py
superface/crewai/superface.py
superface-0.1.4.dist-info/METADATA
superface-0.1.4.dist-info/WHEEL
superface-0.1.4.dist-info/top_level.txt
superface-0.1.4.dist-info/RECORD
