Metadata-Version: 2.4
Name: superface
Version: 0.1.4
Summary: Intelligent Tools for Agentic AI
Author-email: Superface Team <hello@superface.ai>
Project-URL: homepage, https://superface.ai
Project-URL: repository, https://github.com/superfaceai/sdk
Keywords: superface,ai,agent,tools,integrations,api,client,sdk
Requires-Python: >=3.9
Requires-Dist: requests
Requires-Dist: pydantic>=2.0.0
Requires-Dist: crewai>=0.80.0
Requires-Dist: agno>=1.0.0
Provides-Extra: dev
Requires-Dist: pytest; extra == "dev"
